infcolor/__init__.py
infcolor-21.1.dist-info/METADATA
infcolor-21.1.dist-info/WHEEL
infcolor-21.1.dist-info/top_level.txt
infcolor-21.1.dist-info/RECORD
