Metadata-Version: 2.1
Name: infcolor
Version: 21.1
Summary: print(InfColor.info(0))
Author: adamsonScripts
Author-email: TheUnityHD@yandex.ru
Classifier: Programming Language :: Python :: 3
Classifier: License :: OSI Approved :: MIT License
Classifier: Operating System :: OS Independent
Requires-Python: >=3.6
